pyapiq/__init__.py
pyapiq/decorators.py
pyapiq/exceptions.py
pyapiq/parsers.py
pyapiq/py.typed
pyapiq/types.py
pyapiq/utils.py
pyapiq/client/__init__.py
pyapiq/client/_async.py
pyapiq/client/_base.py
pyapiq/client/_sync.py
pyapiq/limiter/__init__.py
pyapiq/limiter/_async.py
pyapiq/limiter/_sync.py
pyapiq/namespace/__init__.py
pyapiq/namespace/_async.py
pyapiq/namespace/_base.py
pyapiq/namespace/_sync.py
pyapiq/requestor/__init__.py
pyapiq/requestor/_async.py
pyapiq/requestor/_sync.py
pyapiq-0.1.6.dist-info/licenses/LICENSE
pyapiq-0.1.6.dist-info/METADATA
pyapiq-0.1.6.dist-info/WHEEL
pyapiq-0.1.6.dist-info/top_level.txt
pyapiq-0.1.6.dist-info/RECORD
