Metadata-Version: 2.4
Name: pyapiq
Version: 0.1.6
Summary: PyAPIq is a modern Python toolkit for building both synchronous and asynchronous API clients with clean, minimal code and full type safety.
Home-page: https://github.com/nessshon/pyapiq
Author: nessshon
License: MIT
Project-URL: Source, https://github.com/nessshon/pyapiq
Project-URL: Issues, https://github.com/nessshon/pyapiq/issues
Keywords: api client async sync http aiohttp requests pydantic
Classifier: Development Status :: 4 - Beta
Classifier: Intended Audience :: Developers
Classifier: Intended Audience :: Financial and Insurance Industry
Classifier: Topic :: Software Development :: Libraries :: Python Modules
Classifier: Programming Language :: Python :: 3.10
Classifier: Programming Language :: Python :: 3.11
Classifier: Programming Language :: Python :: 3.12
Classifier: Programming Language :: Python :: 3.13
Classifier: License :: OSI Approved :: MIT License
Classifier: Operating System :: OS Independent
Classifier: Framework :: AsyncIO
Classifier: Environment :: Console
Requires-Python: >=3.10
License-File: LICENSE
Requires-Dist: aiohttp>=3.7.0
Requires-Dist: pydantic<3.0,>=2.0
Requires-Dist: requests~=2.32.4
Dynamic: author
Dynamic: classifier
Dynamic: description
Dynamic: description-content-type
Dynamic: home-page
Dynamic: keywords
Dynamic: license
Dynamic: license-file
Dynamic: project-url
Dynamic: requires-dist
Dynamic: requires-python
Dynamic: summary
